{"L1-AH-ASC-03": {"modelo": "SINERGY BLUE", "marca": "THYSENKRUPP", "anos_op": 7, "fallas": 20, "criticos": 0}, "L1-US-ASC-03": {"modelo": "SINERGY BLUE", "marca": "THYSENKRUPP", "anos_op": 7, "fallas": 19, "criticos": 0}, "L1-EL-ASC-03": {"modelo": "SINERGY BLUE", "marca": "THYSENKRUPP", "anos_op": 7, "fallas": 72, "criticos": 0}, "L1-PV-ASC-03": {"modelo": "SINERGY BLUE", "marca": "THYSENKRUPP", "anos_op": 7, "fallas": 21, "criticos": 0}, "L5-PE-ASC-01": {"modelo": "SINERGY BLUE", "marca": "THYSENKRUPP", "anos_op": 7, "fallas": 7, "criticos": 0}, "L5-PE-ASC-02": {"modelo": "SINERGY BLUE", "marca": "THYSENKRUPP", "anos_op": 7, "fallas": 18, "criticos": 0}, "L5-PE-ASC-03": {"modelo": "SINERGY BLUE", "marca": "THYSENKRUPP", "anos_op": 7, "fallas": 14, "criticos": 0}, "L5-AG-ASC-01": {"modelo": "SINERGY BLUE", "marca": "THYSENKRUPP", "anos_op": 7, "fallas": 10, "criticos": 0}, "L5-AG-ASC-02": {"modelo": "SINERGY BLUE", "marca": "THYSENKRUPP", "anos_op": 7, "fallas": 4, "criticos": 0}, "L5-AG-ASC-03": {"modelo": "SINERGY BLUE", "marca": "THYSENKRUPP", "anos_op": 7, "fallas": 6, "criticos": 0}, "L5-SI-ASC-01": {"modelo": "SINERGY BLUE", "marca": "THYSENKRUPP", "anos_op": 7, "fallas": 7, "criticos": 0}, "L5-SI-ASC-02": {"modelo": "SINERGY BLUE", "marca": "THYSENKRUPP", "anos_op": 7, "fallas": 6, "criticos": 0}, "L5-SI-ASC-03": {"modelo": "SINERGY BLUE", "marca": "THYSENKRUPP", "anos_op": 7, "fallas": 31, "criticos": 0}, "L5-SJ-ASC-01": {"modelo": "SINERGY BLUE", "marca": "THYSENKRUPP", "anos_op": 7, "fallas": 37, "criticos": 0}, "L5-SJ-ASC-02": {"modelo": "SINERGY BLUE", "marca": "THYSENKRUPP", "anos_op": 7, "fallas": 12, "criticos": 0}, "L5-BE-ASC-02": {"modelo": "SINERGY BLUE", "marca": "THYSENKRUPP", "anos_op": 7, "fallas": 10, "criticos": 0}, "L5-CV-ASC-01": {"modelo": "SINERGY BLUE", "marca": "THYSENKRUPP", "anos_op": 7, "fallas": 5, "criticos": 0}, "L5-CV-ASC-02": {"modelo": "SINERGY BLUE", "marca": "THYSENKRUPP", "anos_op": 7, "fallas": 5, "criticos": 0}, "L5-PB-ASC-01": {"modelo": "SINERGY BLUE", "marca": "THYSENKRUPP", "anos_op": 7, "fallas": 7, "criticos": 0}, "L5-PB-ASC-02": {"modelo": "SINERGY BLUE", "marca": "THYSENKRUPP", "anos_op": 7, "fallas": 6, "criticos": 0}, "L5-PB-ASC-03": {"modelo": "SINERGY BLUE", "marca": "THYSENKRUPP", "anos_op": 7, "fallas": 14, "criticos": 0}, "L5-RA-ASC-01": {"modelo": "SINERGY BLUE", "marca": "THYSENKRUPP", "anos_op": 7, "fallas": 6, "criticos": 0}, "L5-RA-ASC-02": {"modelo": "SINERGY BLUE", "marca": "THYSENKRUPP", "anos_op": 7, "fallas": 1, "criticos": 0}, "L5-CV-ASC-03": {"modelo": "SINERGY BLUE", "marca": "THYSENKRUPP", "anos_op": 7, "fallas": 8, "criticos": 0}, "L5-BE-ASC-01": {"modelo": "SINERGY BLUE", "marca": "THYSENKRUPP", "anos_op": 7, "fallas": 11, "criticos": 0}, "L5-BE-ASC-03": {"modelo": "SINERGY BLUE", "marca": "THYSENKRUPP", "anos_op": 7, "fallas": 23, "criticos": 0}, "L5-MA-ASC-01": {"modelo": "SINERGY BLUE", "marca": "THYSENKRUPP", "anos_op": 7, "fallas": 22, "criticos": 0}, "L5-MA-ASC-02": {"modelo": "SINERGY BLUE", "marca": "THYSENKRUPP", "anos_op": 7, "fallas": 9, "criticos": 0}, "L5-MA-ASC-03": {"modelo": "SINERGY BLUE", "marca": "THYSENKRUPP", "anos_op": 7, "fallas": 3, "criticos": 0}, "L5-RA-ASC-03": {"modelo": "SINERGY BLUE", "marca": "THYSENKRUPP", "anos_op": 7, "fallas": 4, "criticos": 0}, "L3-CAR-ASC-02": {"modelo": "SINERGY BLUE", "marca": "THYSENKRUPP", "anos_op": 7, "fallas": 32, "criticos": 0}, "L3-CAR-ASC-03": {"modelo": "SINERGY BLUE", "marca": "THYSENKRUPP", "anos_op": 7, "fallas": 16, "criticos": 0}, "L3-CCH-ASC-02": {"modelo": "SINERGY BLUE", "marca": "THYSENKRUPP", "anos_op": 7, "fallas": 23, "criticos": 0}, "L3-CCH-ASC-03": {"modelo": "SINERGY BLUE", "marca": "THYSENKRUPP", "anos_op": 7, "fallas": 2, "criticos": 0}, "L3-ESP-ASC-02": {"modelo": "SINERGY BLUE", "marca": "THYSENKRUPP", "anos_op": 7, "fallas": 19, "criticos": 0}, "L3-ESP-ASC-03": {"modelo": "SINERGY BLUE", "marca": "THYSENKRUPP", "anos_op": 7, "fallas": 6, "criticos": 0}, "L3-FCV-ASC-02": {"modelo": "SINERGY BLUE", "marca": "THYSENKRUPP", "anos_op": 7, "fallas": 13, "criticos": 0}, "L3-FCV-ASC-03": {"modelo": "SINERGY BLUE", "marca": "THYSENKRUPP", "anos_op": 7, "fallas": 8, "criticos": 0}, "L3-VFR-ASC-02": {"modelo": "SINERGY BLUE", "marca": "THYSENKRUPP", "anos_op": 7, "fallas": 8, "criticos": 0}, "L3-VFR-ASC-03": {"modelo": "SINERGY BLUE", "marca": "THYSENKRUPP", "anos_op": 7, "fallas": 10, "criticos": 0}, "L3-HOS-ASC-02": {"modelo": "SINERGY BLUE", "marca": "THYSENKRUPP", "anos_op": 7, "fallas": 40, "criticos": 0}, "L3-HOS-ASC-03": {"modelo": "SINERGY BLUE", "marca": "THYSENKRUPP", "anos_op": 7, "fallas": 16, "criticos": 0}, "L3-IRA-ASC-02": {"modelo": "SINERGY BLUE", "marca": "THYSENKRUPP", "anos_op": 7, "fallas": 32, "criticos": 0}, "L3-IRA-ASC-03": {"modelo": "SINERGY BLUE", "marca": "THYSENKRUPP", "anos_op": 7, "fallas": 9, "criticos": 0}, "L3-IRA-ASC-04": {"modelo": "SINERGY BLUE", "marca": "THYSENKRUPP", "anos_op": 7, "fallas": 24, "criticos": 0}, "L3-IRA-ASC-05": {"modelo": "SINERGY BLUE", "marca": "THYSENKRUPP", "anos_op": 7, "fallas": 5, "criticos": 0}, "L3-IRA-ASC-06": {"modelo": "SINERGY BLUE", "marca": "THYSENKRUPP", "anos_op": 7, "fallas": 14, "criticos": 0}, "L3-LIB-ASC-02": {"modelo": "SINERGY BLUE", "marca": "THYSENKRUPP", "anos_op": 7, "fallas": 13, "criticos": 0}, "L3-LIB-ASC-03": {"modelo": "SINERGY BLUE", "marca": "THYSENKRUPP", "anos_op": 7, "fallas": 24, "criticos": 0}, "L3-MAT-ASC-02": {"modelo": "SINERGY BLUE", "marca": "THYSENKRUPP", "anos_op": 7, "fallas": 31, "criticos": 0}, "L3-MAT-ASC-03": {"modelo": "SINERGY BLUE", "marca": "THYSENKRUPP", "anos_op": 7, "fallas": 8, "criticos": 0}, "L3-MEY-ASC-02": {"modelo": "SINERGY BLUE", "marca": "THYSENKRUPP", "anos_op": 7, "fallas": 14, "criticos": 0}, "L3-MEY-ASC-03": {"modelo": "SINERGY BLUE", "marca": "THYSENKRUPP", "anos_op": 7, "fallas": 3, "criticos": 0}, "L3-NUN-ASC-05": {"modelo": "SINERGY BLUE", "marca": "THYSENKRUPP", "anos_op": 7, "fallas": 4, "criticos": 0}, "L3-NUN-ASC-06": {"modelo": "SINERGY BLUE", "marca": "THYSENKRUPP", "anos_op": 7, "fallas": 7, "criticos": 0}, "L3-PAL-ASC-02": {"modelo": "SINERGY BLUE", "marca": "THYSENKRUPP", "anos_op": 7, "fallas": 42, "criticos": 0}, "L3-PAL-ASC-03": {"modelo": "SINERGY BLUE", "marca": "THYSENKRUPP", "anos_op": 7, "fallas": 7, "criticos": 0}, "L3-PCA-ASC-02": {"modelo": "SINERGY BLUE", "marca": "THYSENKRUPP", "anos_op": 7, "fallas": 45, "criticos": 0}, "L3-PCA-ASC-04": {"modelo": "SINERGY BLUE", "marca": "THYSENKRUPP", "anos_op": 7, "fallas": 45, "criticos": 0}, "L3-PCA-ASC-05": {"modelo": "SINERGY BLUE", "marca": "THYSENKRUPP", "anos_op": 7, "fallas": 28, "criticos": 0}, "L3-PCA-ASC-06": {"modelo": "SINERGY BLUE", "marca": "THYSENKRUPP", "anos_op": 7, "fallas": 17, "criticos": 0}, "L3-PZA-ASC-02": {"modelo": "SINERGY BLUE", "marca": "THYSENKRUPP", "anos_op": 7, "fallas": 14, "criticos": 0}, "L3-PZA-ASC-03": {"modelo": "SINERGY BLUE", "marca": "THYSENKRUPP", "anos_op": 7, "fallas": 26, "criticos": 0}, "L3-PZA-ASC-04": {"modelo": "SINERGY BLUE", "marca": "THYSENKRUPP", "anos_op": 7, "fallas": 13, "criticos": 0}, "L3-PZC-ASC-02": {"modelo": "SINERGY BLUE", "marca": "THYSENKRUPP", "anos_op": 7, "fallas": 14, "criticos": 0}, "L3-PZC-ASC-03": {"modelo": "SINERGY BLUE", "marca": "THYSENKRUPP", "anos_op": 7, "fallas": 8, "criticos": 0}, "L3-PZE-ASC-02": {"modelo": "SINERGY BLUE", "marca": "THYSENKRUPP", "anos_op": 7, "fallas": 25, "criticos": 0}, "L3-PZE-ASC-03": {"modelo": "SINERGY BLUE", "marca": "THYSENKRUPP", "anos_op": 7, "fallas": 18, "criticos": 0}, "L3-UCH-ASC-01": {"modelo": "SINERGY BLUE", "marca": "THYSENKRUPP", "anos_op": 7, "fallas": 47, "criticos": 0}, "L3-UCH-ASC-02": {"modelo": "SINERGY BLUE", "marca": "THYSENKRUPP", "anos_op": 7, "fallas": 8, "criticos": 0}, "L3-UCH-ASC-03": {"modelo": "SINERGY BLUE", "marca": "THYSENKRUPP", "anos_op": 7, "fallas": 28, "criticos": 0}, "L3-UCH-ASC-04": {"modelo": "SINERGY BLUE", "marca": "THYSENKRUPP", "anos_op": 7, "fallas": 27, "criticos": 0}, "L6-LEN-S-ASC-03": {"modelo": "SINERGY BLUE", "marca": "THYSENKRUPP", "anos_op": 7, "fallas": 8, "criticos": 0}, "L3-TLIB-ASC-02": {"modelo": "SINERGY BLUE", "marca": "THYSENKRUPP", "anos_op": 7, "fallas": 2, "criticos": 0}, "L3-TLIB-ASC-01": {"modelo": "SINERGY BLUE", "marca": "THYSENKRUPP", "anos_op": 7, "fallas": 1, "criticos": 0}, "L3-VIV-ASC-02": {"modelo": "SINERGY BLUE", "marca": "THYSENKRUPP", "anos_op": 7, "fallas": 12, "criticos": 0}, "L3-VIV-ASC-03": {"modelo": "SINERGY BLUE", "marca": "THYSENKRUPP", "anos_op": 7, "fallas": 17, "criticos": 0}, "L1-LR-ASC-03": {"modelo": "SINERGY BLUE", "marca": "THYSENKRUPP", "anos_op": 12, "fallas": 30, "criticos": 0}, "L1-LR-ASC-04": {"modelo": "SINERGY BLUE", "marca": "THYSENKRUPP", "anos_op": 12, "fallas": 19, "criticos": 0}, "L1-UC-ASC-03": {"modelo": "SINERGY BLUE", "marca": "THYSENKRUPP", "anos_op": 12, "fallas": 29, "criticos": 0}, "L1-SA-ASC-03": {"modelo": "SINERGY BLUE", "marca": "THYSENKRUPP", "anos_op": 11, "fallas": 8, "criticos": 0}, "L1-SA-ASC-04": {"modelo": "SINERGY BLUE", "marca": "THYSENKRUPP", "anos_op": 11, "fallas": 4, "criticos": 0}, "L1-MM-ASC-03": {"modelo": "SINERGY BLUE", "marca": "THYSENKRUPP", "anos_op": 12, "fallas": 36, "criticos": 0}, "L2-RO-ASC-01": {"modelo": "SINERGY BLUE", "marca": "THYSENKRUPP", "anos_op": 12, "fallas": 3, "criticos": 0}, "L2-RO-ASC-02": {"modelo": "SINERGY BLUE", "marca": "THYSENKRUPP", "anos_op": 12, "fallas": 32, "criticos": 0}, "L2-SM-ASC-03": {"modelo": "SINERGY BLUE", "marca": "THYSENKRUPP", "anos_op": 12, "fallas": 15, "criticos": 0}, "L2-CN-ASC-03": {"modelo": "SINERGY BLUE", "marca": "THYSENKRUPP", "anos_op": 12, "fallas": 41, "criticos": 1}, "L1-SA-ASC-01": {"modelo": "SINERGY BLUE", "marca": "THYSENKRUPP", "anos_op": 11, "fallas": 30, "criticos": 0}, "L1-SA-ASC-02": {"modelo": "SINERGY BLUE", "marca": "THYSENKRUPP", "anos_op": 11, "fallas": 11, "criticos": 0}, "L1-NP-ASC-01": {"modelo": "SINERGY BLUE", "marca": "THYSENKRUPP", "anos_op": 9, "fallas": 27, "criticos": 0}, "L1-NP-ASC-02": {"modelo": "SINERGY BLUE", "marca": "THYSENKRUPP", "anos_op": 9, "fallas": 20, "criticos": 0}, "L1-LA-ASC-03": {"modelo": "SINERGY BLUE", "marca": "THYSENKRUPP", "anos_op": 8, "fallas": 34, "criticos": 0}, "L1-RP-ASC-03": {"modelo": "SINERGY BLUE", "marca": "THYSENKRUPP", "anos_op": 8, "fallas": 6, "criticos": 0}, "L1-GO-ASC-01": {"modelo": "SINERGY BLUE", "marca": "THYSENKRUPP", "anos_op": 8, "fallas": 23, "criticos": 0}, "L1-GO-ASC-02": {"modelo": "SINERGY BLUE", "marca": "THYSENKRUPP", "anos_op": 8, "fallas": 12, "criticos": 0}, "L1-GO-ASC-03": {"modelo": "SINERGY BLUE", "marca": "THYSENKRUPP", "anos_op": 8, "fallas": 20, "criticos": 0}, "L1-AL-ASC-03": {"modelo": "SINERGY BLUE", "marca": "THYSENKRUPP", "anos_op": 8, "fallas": 11, "criticos": 0}, "L1-AL-ASC-01": {"modelo": "SINERGY BLUE", "marca": "THYSENKRUPP", "anos_op": 8, "fallas": 16, "criticos": 0}, "L1-AL-ASC-02": {"modelo": "SINERGY BLUE", "marca": "THYSENKRUPP", "anos_op": 8, "fallas": 4, "criticos": 0}, "L2-TO-ASC-01": {"modelo": "SINERGY BLUE", "marca": "THYSENKRUPP", "anos_op": 8, "fallas": 19, "criticos": 1}, "L2-TO-ASC-02": {"modelo": "SINERGY BLUE", "marca": "THYSENKRUPP", "anos_op": 8, "fallas": 11, "criticos": 0}, "L2-LL-ASC-01": {"modelo": "SINERGY BLUE", "marca": "THYSENKRUPP", "anos_op": 9, "fallas": 4, "criticos": 0}, "L2-LL-ASC-02": {"modelo": "SINERGY BLUE", "marca": "THYSENKRUPP", "anos_op": 9, "fallas": 10, "criticos": 0}, "L2-LL-ASC-03": {"modelo": "SINERGY BLUE", "marca": "THYSENKRUPP", "anos_op": 8, "fallas": 23, "criticos": 0}, "L2-LV-ASC-03": {"modelo": "SINERGY BLUE", "marca": "THYSENKRUPP", "anos_op": 8, "fallas": 26, "criticos": 0}, "L2-DE-ASC-03": {"modelo": "SINERGY BLUE", "marca": "THYSENKRUPP", "anos_op": 8, "fallas": 30, "criticos": 0}, "L5-NA-ASC-03": {"modelo": "SINERGY BLUE", "marca": "THYSENKRUPP", "anos_op": 8, "fallas": 22, "criticos": 0}, "L2-LO-ASC-03": {"modelo": "SINERGY BLUE", "marca": "THYSENKRUPP", "anos_op": 8, "fallas": 34, "criticos": 0}, "L2-PQ-ASC-02": {"modelo": "SINERGY BLUE", "marca": "THYSENKRUPP", "anos_op": 8, "fallas": 10, "criticos": 0}, "L2-PQ-ASC-01": {"modelo": "SINERGY BLUE", "marca": "THYSENKRUPP", "anos_op": 8, "fallas": 14, "criticos": 0}, "L1-LM-ASC-03": {"modelo": "SINERGY BLUE", "marca": "THYSENKRUPP", "anos_op": 8, "fallas": 32, "criticos": 0}, "L6-BIO-ASC-02": {"modelo": "SINERGY BLUE", "marca": "THYSENKRUPP", "anos_op": 9, "fallas": 38, "criticos": 0}, "L6-BIO-ASC-03": {"modelo": "SINERGY BLUE", "marca": "THYSENKRUPP", "anos_op": 9, "fallas": 4, "criticos": 0}, "L6-CER-ASC-02": {"modelo": "SINERGY BLUE", "marca": "THYSENKRUPP", "anos_op": 9, "fallas": 16, "criticos": 0}, "L6-CER-ASC-03": {"modelo": "SINERGY BLUE", "marca": "THYSENKRUPP", "anos_op": 9, "fallas": 8, "criticos": 0}, "L6-ESN-ASC-02": {"modelo": "SINERGY BLUE", "marca": "THYSENKRUPP", "anos_op": 9, "fallas": 14, "criticos": 0}, "L6-ESN-ASC-03": {"modelo": "SINERGY BLUE", "marca": "THYSENKRUPP", "anos_op": 9, "fallas": 29, "criticos": 0}, "L6-ESN-ASC-04": {"modelo": "SINERGY BLUE", "marca": "THYSENKRUPP", "anos_op": 9, "fallas": 3, "criticos": 0}, "L6-FRA-ASC-02": {"modelo": "SINERGY BLUE", "marca": "THYSENKRUPP", "anos_op": 9, "fallas": 12, "criticos": 0}, "L6-FRA-ASC-03": {"modelo": "SINERGY BLUE", "marca": "THYSENKRUPP", "anos_op": 9, "fallas": 18, "criticos": 0}, "L6-FRA-ASC-04": {"modelo": "SINERGY BLUE", "marca": "THYSENKRUPP", "anos_op": 9, "fallas": 14, "criticos": 0}, "L6-ISU-ASC-02": {"modelo": "SINERGY BLUE", "marca": "THYSENKRUPP", "anos_op": 9, "fallas": 13, "criticos": 0}, "L6-ISU-ASC-03": {"modelo": "SINERGY BLUE", "marca": "THYSENKRUPP", "anos_op": 9, "fallas": 14, "criticos": 0}, "L6-LEN-S-ASC-02": {"modelo": "SINERGY BLUE", "marca": "THYSENKRUPP", "anos_op": 9, "fallas": 8, "criticos": 0}, "L6-LEN-N-ASC-02": {"modelo": "SINERGY BLUE", "marca": "THYSENKRUPP", "anos_op": 9, "fallas": 26, "criticos": 0}, "L6-LEN-N-ASC-03": {"modelo": "SINERGY BLUE", "marca": "THYSENKRUPP", "anos_op": 9, "fallas": 8, "criticos": 0}, "L6-LVA-ASC-02": {"modelo": "SINERGY BLUE", "marca": "THYSENKRUPP", "anos_op": 9, "fallas": 21, "criticos": 0}, "L6-LVA-ASC-03": {"modelo": "SINERGY BLUE", "marca": "THYSENKRUPP", "anos_op": 9, "fallas": 11, "criticos": 0}, "L6-NUB-ASC-01": {"modelo": "SINERGY BLUE", "marca": "THYSENKRUPP", "anos_op": 9, "fallas": 45, "criticos": 0}, "L6-NUB-ASC-02": {"modelo": "SINERGY BLUE", "marca": "THYSENKRUPP", "anos_op": 9, "fallas": 6, "criticos": 0}, "L6-NUB-ASC-03": {"modelo": "SINERGY BLUE", "marca": "THYSENKRUPP", "anos_op": 9, "fallas": 12, "criticos": 0}, "L6-NUB-ASC-04": {"modelo": "SINERGY BLUE", "marca": "THYSENKRUPP", "anos_op": 9, "fallas": 10, "criticos": 0}, "L6-NUO-ASC-02": {"modelo": "SINERGY BLUE", "marca": "THYSENKRUPP", "anos_op": 9, "fallas": 33, "criticos": 0}, "L6-NUO-ASC-03": {"modelo": "SINERGY BLUE", "marca": "THYSENKRUPP", "anos_op": 9, "fallas": 9, "criticos": 0}, "L6-NUO-ASC-04": {"modelo": "SINERGY BLUE", "marca": "THYSENKRUPP", "anos_op": 9, "fallas": 3, "criticos": 0}, "L6-PAC-ASC-02": {"modelo": "SINERGY BLUE", "marca": "THYSENKRUPP", "anos_op": 9, "fallas": 24, "criticos": 0}, "L6-PAC-ASC-03": {"modelo": "SINERGY BLUE", "marca": "THYSENKRUPP", "anos_op": 9, "fallas": 19, "criticos": 0}, "L6-TC-ASC-01": {"modelo": "SINERGY BLUE", "marca": "THYSENKRUPP", "anos_op": 9, "fallas": 4, "criticos": 0}, "L6-TC-ASC-02": {"modelo": "SINERGY BLUE", "marca": "THYSENKRUPP", "anos_op": 9, "fallas": 3, "criticos": 0}, "L6-TC-ASC-03": {"modelo": "SINERGY BLUE", "marca": "THYSENKRUPP", "anos_op": 9, "fallas": 0, "criticos": 0}, "L1-SEA-ASC-01": {"modelo": "Expert XXI", "marca": "THYSENKRUPP", "anos_op": 23, "fallas": 8, "criticos": 0}, "L1-SEA-ASC-02": {"modelo": "Expert XXI", "marca": "THYSENKRUPP", "anos_op": 23, "fallas": 26, "criticos": 0}, "L1-EC-ASC-01": {"modelo": "Expert XXI", "marca": "THYSENKRUPP", "anos_op": 21, "fallas": 36, "criticos": 0}, "L2-AV-ASC-01": {"modelo": "Expert XXI", "marca": "THYSENKRUPP", "anos_op": 20, "fallas": 8, "criticos": 0}, "L2-AV-ASC-02": {"modelo": "Expert XXI", "marca": "THYSENKRUPP", "anos_op": 20, "fallas": 22, "criticos": 0}, "L2-AV-ASC-03": {"modelo": "Expert XXI", "marca": "THYSENKRUPP", "anos_op": 20, "fallas": 22, "criticos": 0}, "L2-AV-ASC-04": {"modelo": "Expert XXI", "marca": "THYSENKRUPP", "anos_op": 20, "fallas": 15, "criticos": 0}, "L2-ZA-ASC-01": {"modelo": "Expert XXI", "marca": "THYSENKRUPP", "anos_op": 20, "fallas": 23, "criticos": 0}, "L2-ZA-ASC-02": {"modelo": "Expert XXI", "marca": "THYSENKRUPP", "anos_op": 20, "fallas": 16, "criticos": 0}, "L2-ZA-ASC-03": {"modelo": "Expert XXI", "marca": "THYSENKRUPP", "anos_op": 20, "fallas": 47, "criticos": 0}, "L2-DO-ASC-02": {"modelo": "Expert XXI", "marca": "THYSENKRUPP", "anos_op": 20, "fallas": 18, "criticos": 0}, "L2-DO-ASC-03": {"modelo": "Expert XXI", "marca": "THYSENKRUPP", "anos_op": 20, "fallas": 49, "criticos": 0}, "L2-DO-ASC-01": {"modelo": "Expert XXI", "marca": "THYSENKRUPP", "anos_op": 20, "fallas": 4, "criticos": 0}, "L2-EI-ASC-01": {"modelo": "Expert XXI", "marca": "THYSENKRUPP", "anos_op": 21, "fallas": 12, "criticos": 0}, "L2-EI-ASC-02": {"modelo": "Expert XXI", "marca": "THYSENKRUPP", "anos_op": 21, "fallas": 46, "criticos": 0}, "L2-EI-ASC-03": {"modelo": "Expert XXI", "marca": "THYSENKRUPP", "anos_op": 21, "fallas": 52, "criticos": 0}, "L2-CE-ASC-01": {"modelo": "Expert XXI", "marca": "THYSENKRUPP", "anos_op": 21, "fallas": 3, "criticos": 0}, "L2-CE-ASC-02": {"modelo": "Expert XXI", "marca": "THYSENKRUPP", "anos_op": 21, "fallas": 17, "criticos": 0}, "L2-CE-ASC-03": {"modelo": "Expert XXI", "marca": "THYSENKRUPP", "anos_op": 21, "fallas": 11, "criticos": 0}, "L4-COL-ASC-01": {"modelo": "Expert XXI", "marca": "THYSENKRUPP", "anos_op": 21, "fallas": 5, "criticos": 0}, "L4-COL-ASC-02": {"modelo": "Expert XXI", "marca": "THYSENKRUPP", "anos_op": 21, "fallas": 16, "criticos": 0}, "L4-COL-ASC-03": {"modelo": "Expert XXI", "marca": "THYSENKRUPP", "anos_op": 21, "fallas": 19, "criticos": 1}, "L4-BIL-ASC-01": {"modelo": "Expert XXI", "marca": "THYSENKRUPP", "anos_op": 21, "fallas": 5, "criticos": 0}, "L4-BIL-ASC-02": {"modelo": "Expert XXI", "marca": "THYSENKRUPP", "anos_op": 21, "fallas": 10, "criticos": 0}, "L4-BIL-ASC-03": {"modelo": "Expert XXI", "marca": "THYSENKRUPP", "anos_op": 21, "fallas": 9, "criticos": 1}, "L4-PEG-ASC-01": {"modelo": "Expert XXI", "marca": "THYSENKRUPP", "anos_op": 21, "fallas": 28, "criticos": 0}, "L4-PEG-ASC-02": {"modelo": "Expert XXI", "marca": "THYSENKRUPP", "anos_op": 21, "fallas": 23, "criticos": 0}, "L4-PDG-ASC-01": {"modelo": "Expert XXI", "marca": "THYSENKRUPP", "anos_op": 21, "fallas": 9, "criticos": 0}, "L4-PDG-ASC-02": {"modelo": "Expert XXI", "marca": "THYSENKRUPP", "anos_op": 21, "fallas": 11, "criticos": 0}, "L4-PDG-ASC-03": {"modelo": "Expert XXI", "marca": "THYSENKRUPP", "anos_op": 21, "fallas": 34, "criticos": 0}, "L4-HSR-ASC-01": {"modelo": "Expert XXI", "marca": "THYSENKRUPP", "anos_op": 21, "fallas": 37, "criticos": 0}, "L4-HSR-ASC-02": {"modelo": "Expert XXI", "marca": "THYSENKRUPP", "anos_op": 21, "fallas": 23, "criticos": 0}, "L4-HSR-ASC-03": {"modelo": "Expert XXI", "marca": "THYSENKRUPP", "anos_op": 21, "fallas": 23, "criticos": 0}, "L4-HSR-ASC-04": {"modelo": "Expert XXI", "marca": "THYSENKRUPP", "anos_op": 21, "fallas": 35, "criticos": 0}, "L4-LPR-ASC-01": {"modelo": "Expert XXI", "marca": "THYSENKRUPP", "anos_op": 20, "fallas": 14, "criticos": 0}, "L4-LPR-ASC-02": {"modelo": "Expert XXI", "marca": "THYSENKRUPP", "anos_op": 20, "fallas": 21, "criticos": 0}, "L4-LPR-ASC-03": {"modelo": "Expert XXI", "marca": "THYSENKRUPP", "anos_op": 20, "fallas": 41, "criticos": 0}, "L4-LPR-ASC-04": {"modelo": "Expert XXI", "marca": "THYSENKRUPP", "anos_op": 20, "fallas": 43, "criticos": 0}, "L4-LTO-ASC-01": {"modelo": "Expert XXI", "marca": "THYSENKRUPP", "anos_op": 20, "fallas": 15, "criticos": 0}, "L4-LTO-ASC-02": {"modelo": "Expert XXI", "marca": "THYSENKRUPP", "anos_op": 20, "fallas": 7, "criticos": 0}, "L4-LTO-ASC-03": {"modelo": "Expert XXI", "marca": "THYSENKRUPP", "anos_op": 20, "fallas": 37, "criticos": 0}, "L4-LTO-ASC-04": {"modelo": "Expert XXI", "marca": "THYSENKRUPP", "anos_op": 20, "fallas": 20, "criticos": 0}, "L4-MAC-ASC-01": {"modelo": "Expert XXI", "marca": "THYSENKRUPP", "anos_op": 20, "fallas": 10, "criticos": 0}, "L4-MAC-ASC-02": {"modelo": "Expert XXI", "marca": "THYSENKRUPP", "anos_op": 20, "fallas": 11, "criticos": 0}, "L4-MAC-ASC-03": {"modelo": "Expert XXI", "marca": "THYSENKRUPP", "anos_op": 20, "fallas": 23, "criticos": 0}, "L4-MAC-ASC-04": {"modelo": "Expert XXI", "marca": "THYSENKRUPP", "anos_op": 20, "fallas": 23, "criticos": 0}, "L4-LME-ASC-01": {"modelo": "Expert XXI", "marca": "THYSENKRUPP", "anos_op": 21, "fallas": 13, "criticos": 0}, "L4-LME-ASC-02": {"modelo": "Expert XXI", "marca": "THYSENKRUPP", "anos_op": 21, "fallas": 18, "criticos": 0}, "L4-LME-ASC-03": {"modelo": "Expert XXI", "marca": "THYSENKRUPP", "anos_op": 21, "fallas": 17, "criticos": 0}, "L4-LOR-ASC-01": {"modelo": "Expert XXI", "marca": "THYSENKRUPP", "anos_op": 21, "fallas": 11, "criticos": 0}, "L4-LOR-ASC-02": {"modelo": "Expert XXI", "marca": "THYSENKRUPP", "anos_op": 21, "fallas": 3, "criticos": 0}, "L4-LOR-ASC-03": {"modelo": "Expert XXI", "marca": "THYSENKRUPP", "anos_op": 21, "fallas": 14, "criticos": 0}, "L4-PPA-ASC-01": {"modelo": "Expert XXI", "marca": "THYSENKRUPP", "anos_op": 21, "fallas": 6, "criticos": 0}, "L4-PPA-ASC-02": {"modelo": "Expert XXI", "marca": "THYSENKRUPP", "anos_op": 21, "fallas": 27, "criticos": 0}, "L4-PPA-ASC-03": {"modelo": "Expert XXI", "marca": "THYSENKRUPP", "anos_op": 21, "fallas": 35, "criticos": 0}, "L4-RGR-ASC-03": {"modelo": "Expert XXI", "marca": "THYSENKRUPP", "anos_op": 21, "fallas": 23, "criticos": 0}, "L4-RGR-ASC-04": {"modelo": "Expert XXI", "marca": "THYSENKRUPP", "anos_op": 21, "fallas": 27, "criticos": 0}, "L4-RGR-ASC-05": {"modelo": "Expert XXI", "marca": "THYSENKRUPP", "anos_op": 21, "fallas": 17, "criticos": 0}, "L4-RQ-ASC-01": {"modelo": "Expert XXI", "marca": "THYSENKRUPP", "anos_op": 20, "fallas": 5, "criticos": 0}, "L4-RQ-ASC-02": {"modelo": "Expert XXI", "marca": "THYSENKRUPP", "anos_op": 20, "fallas": 14, "criticos": 0}, "L4-RQ-ASC-03": {"modelo": "Expert XXI", "marca": "THYSENKRUPP", "anos_op": 20, "fallas": 13, "criticos": 0}, "L4-RQ-ASC-04": {"modelo": "Expert XXI", "marca": "THYSENKRUPP", "anos_op": 20, "fallas": 25, "criticos": 0}, "L4-RQ-ASC-05": {"modelo": "Expert XXI", "marca": "THYSENKRUPP", "anos_op": 20, "fallas": 42, "criticos": 0}, "L4-SBO-ASC-01": {"modelo": "Expert XXI", "marca": "THYSENKRUPP", "anos_op": 21, "fallas": 3, "criticos": 0}, "L4-SBO-ASC-02": {"modelo": "Expert XXI", "marca": "THYSENKRUPP", "anos_op": 21, "fallas": 10, "criticos": 0}, "L4-SBO-ASC-03": {"modelo": "Expert XXI", "marca": "THYSENKRUPP", "anos_op": 21, "fallas": 32, "criticos": 0}, "L4-TOB-ASC-01": {"modelo": "Expert XXI", "marca": "THYSENKRUPP", "anos_op": 21, "fallas": 11, "criticos": 0}, "L4-TOB-ASC-02": {"modelo": "Expert XXI", "marca": "THYSENKRUPP", "anos_op": 21, "fallas": 11, "criticos": 0}, "L4-TOB-ASC-03": {"modelo": "Expert XXI", "marca": "THYSENKRUPP", "anos_op": 21, "fallas": 21, "criticos": 0}, "L4-TOB-ASC-04": {"modelo": "Expert XXI", "marca": "THYSENKRUPP", "anos_op": 21, "fallas": 17, "criticos": 0}, "L4-TOB-ASC-05": {"modelo": "Expert XXI", "marca": "THYSENKRUPP", "anos_op": 21, "fallas": 20, "criticos": 0}, "L4-TOB-ASC-06": {"modelo": "Expert XXI", "marca": "THYSENKRUPP", "anos_op": 21, "fallas": 31, "criticos": 0}, "L4-VVA-ASC-01": {"modelo": "Expert XXI", "marca": "THYSENKRUPP", "anos_op": 21, "fallas": 8, "criticos": 0}, "L4-VVA-ASC-02": {"modelo": "Expert XXI", "marca": "THYSENKRUPP", "anos_op": 21, "fallas": 28, "criticos": 0}, "L4-VVA-ASC-03": {"modelo": "Expert XXI", "marca": "THYSENKRUPP", "anos_op": 21, "fallas": 10, "criticos": 0}, "L4-VVA-ASC-04": {"modelo": "Expert XXI", "marca": "THYSENKRUPP", "anos_op": 21, "fallas": 15, "criticos": 0}, "L4-VMA-ASC-01": {"modelo": "Expert XXI", "marca": "THYSENKRUPP", "anos_op": 20, "fallas": 22, "criticos": 1}, "L4-VMA-ASC-02": {"modelo": "Expert XXI", "marca": "THYSENKRUPP", "anos_op": 20, "fallas": 27, "criticos": 0}, "L5-DS-ASC-03": {"modelo": "SINERGY MHC2", "marca": "THYSENKRUPP", "anos_op": 4, "fallas": 72, "criticos": 1}, "L5-LS-ASC-01": {"modelo": "SINERGY MHC2", "marca": "THYSENKRUPP", "anos_op": 4, "fallas": 42, "criticos": 0}, "L5-BQ-ASC-03": {"modelo": "SINERGY MHC2", "marca": "THYSENKRUPP", "anos_op": 4, "fallas": 62, "criticos": 0}, "L5-NA-ASC-01": {"modelo": "SINERGY E-CORE", "marca": "THYSENKRUPP", "anos_op": 8, "fallas": 14, "criticos": 0}, "L5-NA-ASC-02": {"modelo": "SINERGY E-CORE", "marca": "THYSENKRUPP", "anos_op": 8, "fallas": 25, "criticos": 0}, "L1-AH-ASC-01": {"modelo": "SINERGY E-CORE", "marca": "THYSENKRUPP", "anos_op": 7, "fallas": 25, "criticos": 0}, "L1-AH-ASC-02": {"modelo": "SINERGY E-CORE", "marca": "THYSENKRUPP", "anos_op": 7, "fallas": 45, "criticos": 0}, "L1-EL-ASC-01": {"modelo": "SINERGY E-CORE", "marca": "THYSENKRUPP", "anos_op": 7, "fallas": 23, "criticos": 0}, "L1-EL-ASC-02": {"modelo": "SINERGY E-CORE", "marca": "THYSENKRUPP", "anos_op": 7, "fallas": 32, "criticos": 0}, "L1-LA-ASC-01": {"modelo": "SINERGY E-CORE", "marca": "THYSENKRUPP", "anos_op": 8, "fallas": 49, "criticos": 0}, "L1-LA-ASC-02": {"modelo": "SINERGY E-CORE", "marca": "THYSENKRUPP", "anos_op": 8, "fallas": 22, "criticos": 0}, "L1-RP-ASC-01": {"modelo": "SINERGY E-CORE", "marca": "THYSENKRUPP", "anos_op": 8, "fallas": 12, "criticos": 0}, "L1-RP-ASC-02": {"modelo": "SINERGY E-CORE", "marca": "THYSENKRUPP", "anos_op": 8, "fallas": 31, "criticos": 0}, "L1-SL-ASC-01": {"modelo": "SINERGY E-CORE", "marca": "THYSENKRUPP", "anos_op": 7, "fallas": 23, "criticos": 0}, "L1-SL-ASC-02": {"modelo": "SINERGY E-CORE", "marca": "THYSENKRUPP", "anos_op": 7, "fallas": 12, "criticos": 0}, "L1-SL-ASC-03": {"modelo": "SINERGY MHC2", "marca": "THYSENKRUPP", "anos_op": 4, "fallas": 44, "criticos": 0}, "L1-PV-ASC-01": {"modelo": "SINERGY E-CORE", "marca": "THYSENKRUPP", "anos_op": 7, "fallas": 20, "criticos": 0}, "L1-PV-ASC-02": {"modelo": "SINERGY E-CORE", "marca": "THYSENKRUPP", "anos_op": 7, "fallas": 14, "criticos": 0}, "L2-AN-ASC-01": {"modelo": "SINERGY E-CORE", "marca": "THYSENKRUPP", "anos_op": 8, "fallas": 22, "criticos": 0}, "L2-AN-ASC-02": {"modelo": "SINERGY E-CORE", "marca": "THYSENKRUPP", "anos_op": 8, "fallas": 19, "criticos": 0}, "L2-AN-ASC-03": {"modelo": "SINERGY E-CORE", "marca": "THYSENKRUPP", "anos_op": 8, "fallas": 37, "criticos": 0}, "L2-AN-ASC-04": {"modelo": "SINERGY E-CORE", "marca": "THYSENKRUPP", "anos_op": 8, "fallas": 27, "criticos": 0}, "L2-AN-ASC-05": {"modelo": "SINERGY E-CORE", "marca": "THYSENKRUPP", "anos_op": 8, "fallas": 45, "criticos": 0}, "L2-AN-ASC-06": {"modelo": "SINERGY E-CORE", "marca": "THYSENKRUPP", "anos_op": 8, "fallas": 28, "criticos": 0}, "L2-LV-ASC-01": {"modelo": "SINERGY E-CORE", "marca": "THYSENKRUPP", "anos_op": 8, "fallas": 27, "criticos": 0}, "L2-LV-ASC-02": {"modelo": "SINERGY E-CORE", "marca": "THYSENKRUPP", "anos_op": 8, "fallas": 15, "criticos": 0}, "L2-DE-ASC-01": {"modelo": "SINERGY E-CORE", "marca": "THYSENKRUPP", "anos_op": 8, "fallas": 10, "criticos": 0}, "L2-DE-ASC-02": {"modelo": "SINERGY E-CORE", "marca": "THYSENKRUPP", "anos_op": 8, "fallas": 12, "criticos": 0}, "L2-LO-ASC-01": {"modelo": "SINERGY E-CORE", "marca": "THYSENKRUPP", "anos_op": 8, "fallas": 24, "criticos": 0}, "L2-LO-ASC-02": {"modelo": "SINERGY E-CORE", "marca": "THYSENKRUPP", "anos_op": 8, "fallas": 32, "criticos": 0}, "L1-LM-ASC-01": {"modelo": "SINERGY E-CORE", "marca": "THYSENKRUPP", "anos_op": 8, "fallas": 54, "criticos": 0}, "L1-LM-ASC-02": {"modelo": "SINERGY E-CORE", "marca": "THYSENKRUPP", "anos_op": 8, "fallas": 31, "criticos": 0}, "L3-CAR-ASC-01": {"modelo": "EVOLUTION", "marca": "THYSENKRUPP", "anos_op": 7, "fallas": 17, "criticos": 0}, "L3-CCH-ASC-01": {"modelo": "EVOLUTION", "marca": "THYSENKRUPP", "anos_op": 7, "fallas": 27, "criticos": 0}, "L3-ESP-ASC-01": {"modelo": "EVOLUTION", "marca": "THYSENKRUPP", "anos_op": 7, "fallas": 9, "criticos": 0}, "L3-FCV-ASC-01": {"modelo": "EVOLUTION", "marca": "THYSENKRUPP", "anos_op": 7, "fallas": 23, "criticos": 0}, "L3-VFR-ASC-01": {"modelo": "EVOLUTION", "marca": "THYSENKRUPP", "anos_op": 7, "fallas": 15, "criticos": 0}, "L3-HOS-ASC-01": {"modelo": "EVOLUTION", "marca": "THYSENKRUPP", "anos_op": 7, "fallas": 23, "criticos": 0}, "L3-IRA-ASC-01": {"modelo": "EVOLUTION", "marca": "THYSENKRUPP", "anos_op": 7, "fallas": 31, "criticos": 0}, "L3-LIB-ASC-05": {"modelo": "EVOLUTION", "marca": "THYSENKRUPP", "anos_op": 7, "fallas": 17, "criticos": 0}, "L3-MAT-ASC-01": {"modelo": "EVOLUTION", "marca": "THYSENKRUPP", "anos_op": 7, "fallas": 8, "criticos": 0}, "L3-MEY-ASC-01": {"modelo": "EVOLUTION", "marca": "THYSENKRUPP", "anos_op": 7, "fallas": 21, "criticos": 0}, "L3-PAL-ASC-01": {"modelo": "EVOLUTION", "marca": "THYSENKRUPP", "anos_op": 7, "fallas": 34, "criticos": 0}, "L3-PCA-ASC-01": {"modelo": "EVOLUTION", "marca": "THYSENKRUPP", "anos_op": 7, "fallas": 28, "criticos": 0}, "L3-PZA-ASC-01": {"modelo": "EVOLUTION", "marca": "THYSENKRUPP", "anos_op": 7, "fallas": 17, "criticos": 0}, "L3-PZC-ASC-01": {"modelo": "EVOLUTION", "marca": "THYSENKRUPP", "anos_op": 7, "fallas": 25, "criticos": 0}, "L3-PZE-ASC-01": {"modelo": "EVOLUTION", "marca": "THYSENKRUPP", "anos_op": 7, "fallas": 21, "criticos": 0}, "L3-LIB-ASC-01": {"modelo": "EVOLUTION", "marca": "THYSENKRUPP", "anos_op": 7, "fallas": 10, "criticos": 0}, "L6-BIO-ASC-01": {"modelo": "EVOLUTION", "marca": "THYSENKRUPP", "anos_op": 9, "fallas": 28, "criticos": 0}, "L6-CER-ASC-01": {"modelo": "EVOLUTION", "marca": "THYSENKRUPP", "anos_op": 9, "fallas": 13, "criticos": 0}, "L6-ESN-ASC-01": {"modelo": "EVOLUTION", "marca": "THYSENKRUPP", "anos_op": 9, "fallas": 15, "criticos": 0}, "L6-FRA-ASC-01": {"modelo": "EVOLUTION", "marca": "THYSENKRUPP", "anos_op": 9, "fallas": 23, "criticos": 0}, "L6-FRA-ASC-05": {"modelo": "EVOLUTION", "marca": "THYSENKRUPP", "anos_op": 9, "fallas": 16, "criticos": 0}, "L6-ISU-ASC-01": {"modelo": "EVOLUTION", "marca": "THYSENKRUPP", "anos_op": 9, "fallas": 60, "criticos": 0}, "L6-LEN-S-ASC-01": {"modelo": "EVOLUTION", "marca": "THYSENKRUPP", "anos_op": 9, "fallas": 14, "criticos": 0}, "L6-LEN-N-ASC-01": {"modelo": "EVOLUTION", "marca": "THYSENKRUPP", "anos_op": 9, "fallas": 32, "criticos": 0}, "L6-LVA-ASC-01": {"modelo": "EVOLUTION", "marca": "THYSENKRUPP", "anos_op": 9, "fallas": 16, "criticos": 0}, "L6-NUO-ASC-01": {"modelo": "EVOLUTION", "marca": "THYSENKRUPP", "anos_op": 9, "fallas": 18, "criticos": 0}, "L6-PAC-ASC-01": {"modelo": "EVOLUTION", "marca": "THYSENKRUPP", "anos_op": 9, "fallas": 24, "criticos": 0}, "L3-VIV-ASC-01": {"modelo": "EVOLUTION", "marca": "THYSENKRUPP", "anos_op": 7, "fallas": 9, "criticos": 0}, "L2-EB-ASC-01": {"modelo": "SINERGY MHC2", "marca": "THYSENKRUPP", "anos_op": 3, "fallas": 43, "criticos": 0}, "L2-EB-ASC-02": {"modelo": "SINERGY MHC2", "marca": "THYSENKRUPP", "anos_op": 3, "fallas": 34, "criticos": 0}, "L2-EB-ASC-03": {"modelo": "SINERGY MHC2", "marca": "THYSENKRUPP", "anos_op": 3, "fallas": 10, "criticos": 0}, "L2-OB-ASC-01": {"modelo": "SINERGY MHC2", "marca": "THYSENKRUPP", "anos_op": 3, "fallas": 35, "criticos": 0}, "L2-OB-ASC-02": {"modelo": "SINERGY MHC2", "marca": "THYSENKRUPP", "anos_op": 3, "fallas": 14, "criticos": 0}, "L2-OB-ASC-03": {"modelo": "SINERGY MHC2", "marca": "THYSENKRUPP", "anos_op": 3, "fallas": 22, "criticos": 0}, "L2-CM-ASC-01": {"modelo": "SINERGY MHC2", "marca": "THYSENKRUPP", "anos_op": 3, "fallas": 38, "criticos": 0}, "L2-CM-ASC-02": {"modelo": "SINERGY MHC2", "marca": "THYSENKRUPP", "anos_op": 3, "fallas": 21, "criticos": 0}, "L2-CM-ASC-03": {"modelo": "SINERGY MHC2", "marca": "THYSENKRUPP", "anos_op": 3, "fallas": 32, "criticos": 0}, "L2-EO-ASC-01": {"modelo": "SINERGY MHC2", "marca": "THYSENKRUPP", "anos_op": 3, "fallas": 32, "criticos": 0}, "L2-EO-ASC-02": {"modelo": "SINERGY MHC2", "marca": "THYSENKRUPP", "anos_op": 3, "fallas": 51, "criticos": 1}, "L2-EO-ASC-03": {"modelo": "SINERGY MHC2", "marca": "THYSENKRUPP", "anos_op": 3, "fallas": 27, "criticos": 0}, "L2-EO-ASC-04": {"modelo": "SINERGY MHC2", "marca": "THYSENKRUPP", "anos_op": 3, "fallas": 32, "criticos": 0}, "L3-FER-ASC-01": {"modelo": "SINERGY MHC2", "marca": "THYSENKRUPP", "anos_op": 3, "fallas": 28, "criticos": 0}, "L3-FER-ASC-02": {"modelo": "SINERGY MHC2", "marca": "THYSENKRUPP", "anos_op": 3, "fallas": 24, "criticos": 0}, "L3-FER-ASC-03": {"modelo": "SINERGY MHC2", "marca": "THYSENKRUPP", "anos_op": 3, "fallas": 7, "criticos": 0}, "L3-LCR-ASC-01": {"modelo": "SINERGY MHC2", "marca": "THYSENKRUPP", "anos_op": 3, "fallas": 38, "criticos": 0}, "L3-LCR-ASC-02": {"modelo": "SINERGY MHC2", "marca": "THYSENKRUPP", "anos_op": 3, "fallas": 21, "criticos": 0}, "L3-LCR-ASC-03": {"modelo": "SINERGY MHC2", "marca": "THYSENKRUPP", "anos_op": 3, "fallas": 34, "criticos": 1}, "L3-PQU-ASC-01": {"modelo": "SINERGY MHC2", "marca": "THYSENKRUPP", "anos_op": 3, "fallas": 41, "criticos": 0}, "L3-PQU-ASC-02": {"modelo": "SINERGY MHC2", "marca": "THYSENKRUPP", "anos_op": 3, "fallas": 44, "criticos": 0}, "L3-PQU-ASC-03": {"modelo": "SINERGY MHC2", "marca": "THYSENKRUPP", "anos_op": 3, "fallas": 13, "criticos": 0}, "L3-PQU-ASC-04": {"modelo": "SINERGY MHC2", "marca": "THYSENKRUPP", "anos_op": 3, "fallas": 18, "criticos": 0}, "L2-PT-ASC-01": {"modelo": "MCP 5", "marca": "THYSENKRUPP", "anos_op": 22, "fallas": 46, "criticos": 0}, "L2-PT-ASC-02": {"modelo": "MCP 5", "marca": "THYSENKRUPP", "anos_op": 22, "fallas": 14, "criticos": 0}, "L2-PT-ASC-03": {"modelo": "MCP 5", "marca": "THYSENKRUPP", "anos_op": 22, "fallas": 21, "criticos": 0}, "L2-CB-ASC-01": {"modelo": "MCP 5", "marca": "THYSENKRUPP", "anos_op": 22, "fallas": 14, "criticos": 0}, "L2-CB-ASC-02": {"modelo": "MCP 5", "marca": "THYSENKRUPP", "anos_op": 22, "fallas": 15, "criticos": 0}, "L2-CB-ASC-03": {"modelo": "MCP 5", "marca": "THYSENKRUPP", "anos_op": 22, "fallas": 57, "criticos": 0}, "L5-QN-ASC-01": {"modelo": "MCP 5", "marca": "THYSENKRUPP", "anos_op": 22, "fallas": 3, "criticos": 0}, "L5-QN-ASC-02": {"modelo": "MCP 5", "marca": "THYSENKRUPP", "anos_op": 22, "fallas": 5, "criticos": 0}, "L5-QN-ASC-03": {"modelo": "MCP 5", "marca": "THYSENKRUPP", "anos_op": 22, "fallas": 25, "criticos": 0}, "L5-RC-ASC-01": {"modelo": "MCP 5", "marca": "THYSENKRUPP", "anos_op": 22, "fallas": 23, "criticos": 0}, "L5-RC-ASC-02": {"modelo": "MCP 5", "marca": "THYSENKRUPP", "anos_op": 22, "fallas": 27, "criticos": 0}, "L5-RC-ASC-03": {"modelo": "MCP 5", "marca": "THYSENKRUPP", "anos_op": 22, "fallas": 37, "criticos": 0}, "L2-EP-ASC-01": {"modelo": "MCP 5", "marca": "THYSENKRUPP", "anos_op": 22, "fallas": 10, "criticos": 0}, "L2-EP-ASC-02": {"modelo": "MCP 5", "marca": "THYSENKRUPP", "anos_op": 22, "fallas": 19, "criticos": 0}, "L2-EP-ASC-03": {"modelo": "MCP 5", "marca": "THYSENKRUPP", "anos_op": 22, "fallas": 37, "criticos": 0}, "L2-LC-ASC-01": {"modelo": "MCP 5", "marca": "THYSENKRUPP", "anos_op": 22, "fallas": 40, "criticos": 0}, "L2-LC-ASC-02": {"modelo": "MCP 5", "marca": "THYSENKRUPP", "anos_op": 22, "fallas": 23, "criticos": 0}, "L2-LC-ASC-03": {"modelo": "MCP 5", "marca": "THYSENKRUPP", "anos_op": 22, "fallas": 82, "criticos": 0}, "L4-RGR-ASC-01": {"modelo": "MCP 7", "marca": "THYSENKRUPP", "anos_op": 21, "fallas": 15, "criticos": 1}, "L5-PZ-ASC-01": {"modelo": "BOETTICHER", "marca": "THYSENKRUPP", "anos_op": 26, "fallas": 24, "criticos": 0}, "L5-PZ-ASC-02": {"modelo": "BOETTICHER", "marca": "THYSENKRUPP", "anos_op": 26, "fallas": 13, "criticos": 0}, "L5-PZ-ASC-03": {"modelo": "BOETTICHER", "marca": "THYSENKRUPP", "anos_op": 26, "fallas": 46, "criticos": 0}, "L4-RGR-ASC-02": {"modelo": "MCP 7", "marca": "THYSENKRUPP", "anos_op": 21, "fallas": 12, "criticos": 0}, "L1-SP-ASC-01": {"modelo": "GEN2 COMFORT", "marca": "OTIS", "anos_op": 4, "fallas": 21, "criticos": 0}, "L1-SP-ASC-02": {"modelo": "GEN2 COMFORT", "marca": "OTIS", "anos_op": 4, "fallas": 3, "criticos": 0}, "L1-PJ-ASC-01": {"modelo": "GEN2 COMFORT", "marca": "OTIS", "anos_op": 17, "fallas": 6, "criticos": 0}, "L1-PJ-ASC-02": {"modelo": "GEN2 COMFORT", "marca": "OTIS", "anos_op": 17, "fallas": 11, "criticos": 1}, "L1-CH-ASC-01": {"modelo": "GEN2 COMFORT", "marca": "OTIS", "anos_op": 17, "fallas": 15, "criticos": 0}, "L1-CH-ASC-02": {"modelo": "GEN2 COMFORT", "marca": "OTIS", "anos_op": 17, "fallas": 13, "criticos": 0}, "L1-CH-ASC-03": {"modelo": "GEN2 COMFORT", "marca": "OTIS", "anos_op": 17, "fallas": 29, "criticos": 0}, "L1-UC-ASC-01": {"modelo": "GEN2 REGEN", "marca": "OTIS", "anos_op": 12, "fallas": 11, "criticos": 0}, "L1-UC-ASC-02": {"modelo": "GEN2 REGEN", "marca": "OTIS", "anos_op": 12, "fallas": 6, "criticos": 0}, "L1-BA-ASC-01": {"modelo": "GEN2 REGEN", "marca": "OTIS", "anos_op": 15, "fallas": 23, "criticos": 0}, "L1-MM-ASC-01": {"modelo": "GEN2 REGEN", "marca": "OTIS", "anos_op": 12, "fallas": 14, "criticos": 0}, "L1-MM-ASC-02": {"modelo": "GEN2 REGEN", "marca": "OTIS", "anos_op": 12, "fallas": 4, "criticos": 0}, "L1-EM-ASC-01": {"modelo": "GEN2 COMFORT", "marca": "OTIS", "anos_op": 16, "fallas": 16, "criticos": 0}, "L1-MQ-ASC-01": {"modelo": "GEN2 COMFORT", "marca": "OTIS", "anos_op": 16, "fallas": 3, "criticos": 0}, "L1-MQ-ASC-02": {"modelo": "GEN2 COMFORT", "marca": "OTIS", "anos_op": 16, "fallas": 8, "criticos": 0}, "L1-MQ-ASC-03": {"modelo": "GEN2 COMFORT", "marca": "OTIS", "anos_op": 16, "fallas": 24, "criticos": 0}, "L1-MQ-ASC-04": {"modelo": "GEN2 COMFORT", "marca": "OTIS", "anos_op": 16, "fallas": 20, "criticos": 0}, "L1-HM-ASC-01": {"modelo": "GEN2 COMFORT", "marca": "OTIS", "anos_op": 16, "fallas": 8, "criticos": 0}, "L1-HM-ASC-02": {"modelo": "GEN2 COMFORT", "marca": "OTIS", "anos_op": 16, "fallas": 2, "criticos": 0}, "L1-HM-ASC-03": {"modelo": "GEN2 COMFORT", "marca": "OTIS", "anos_op": 16, "fallas": 52, "criticos": 0}, "L1-LD-ASC-01": {"modelo": "GEN2 COMFORT", "marca": "OTIS", "anos_op": 16, "fallas": 8, "criticos": 0}, "L1-LD-ASC-02": {"modelo": "GEN2 COMFORT", "marca": "OTIS", "anos_op": 16, "fallas": 9, "criticos": 0}, "L1-LD-ASC-03": {"modelo": "GEN2 COMFORT", "marca": "OTIS", "anos_op": 16, "fallas": 46, "criticos": 0}, "L2-SM-ASC-01": {"modelo": "GEN2 REGEN", "marca": "OTIS", "anos_op": 12, "fallas": 6, "criticos": 1}, "L2-SM-ASC-02": {"modelo": "GEN2 REGEN", "marca": "OTIS", "anos_op": 12, "fallas": 2, "criticos": 0}, "L2-CN-ASC-01": {"modelo": "GEN2 REGEN", "marca": "OTIS", "anos_op": 12, "fallas": 5, "criticos": 0}, "L2-CN-ASC-02": {"modelo": "GEN2 REGEN", "marca": "OTIS", "anos_op": 12, "fallas": 25, "criticos": 1}, "L5-PM-ASC-01": {"modelo": "GEN2 COMFORT", "marca": "OTIS", "anos_op": 15, "fallas": 28, "criticos": 0}, "L5-PM-ASC-02": {"modelo": "GEN2 COMFORT", "marca": "OTIS", "anos_op": 15, "fallas": 5, "criticos": 0}, "L5-PM-ASC-03": {"modelo": "GEN2 COMFORT", "marca": "OTIS", "anos_op": 15, "fallas": 27, "criticos": 0}, "L5-PM-ASC-04": {"modelo": "GEN2 COMFORT", "marca": "OTIS", "anos_op": 15, "fallas": 63, "criticos": 0}, "L5-SB-ASC-01": {"modelo": "GEN2 COMFORT", "marca": "OTIS", "anos_op": 15, "fallas": 15, "criticos": 0}, "L5-SB-ASC-02": {"modelo": "GEN2 COMFORT", "marca": "OTIS", "anos_op": 15, "fallas": 7, "criticos": 0}, "L5-SB-ASC-03": {"modelo": "GEN2 COMFORT", "marca": "OTIS", "anos_op": 15, "fallas": 44, "criticos": 1}, "L5-DS-ASC-04": {"modelo": "GEN2 COMFORT", "marca": "OTIS", "anos_op": 15, "fallas": 5, "criticos": 0}, "L5-DS-ASC-02": {"modelo": "GEN2 COMFORT", "marca": "OTIS", "anos_op": 15, "fallas": 0, "criticos": 0}, "L5-DS-ASC-01": {"modelo": "GEN2 COMFORT", "marca": "OTIS", "anos_op": 15, "fallas": 6, "criticos": 0}, "L5-MT-ASC-01": {"modelo": "GEN2 COMFORT", "marca": "OTIS", "anos_op": 15, "fallas": 17, "criticos": 0}, "L5-PA-ASC-01": {"modelo": "GEN2 COMFORT", "marca": "OTIS", "anos_op": 15, "fallas": 25, "criticos": 0}, "L5-BR-ASC-01": {"modelo": "GEN2 COMFORT", "marca": "OTIS", "anos_op": 15, "fallas": 9, "criticos": 0}, "L5-BR-ASC-02": {"modelo": "GEN2 COMFORT", "marca": "OTIS", "anos_op": 15, "fallas": 11, "criticos": 0}, "L5-BR-ASC-03": {"modelo": "GEN2 COMFORT", "marca": "OTIS", "anos_op": 15, "fallas": 25, "criticos": 0}, "L5-BR-ASC-04": {"modelo": "GEN2 COMFORT", "marca": "OTIS", "anos_op": 15, "fallas": 5, "criticos": 0}, "L5-PU-ASC-01": {"modelo": "GEN2 COMFORT", "marca": "OTIS", "anos_op": 16, "fallas": 9, "criticos": 0}, "L5-PU-ASC-02": {"modelo": "GEN2 COMFORT", "marca": "OTIS", "anos_op": 16, "fallas": 9, "criticos": 0}, "L5-PU-ASC-03": {"modelo": "GEN2 COMFORT", "marca": "OTIS", "anos_op": 16, "fallas": 31, "criticos": 0}, "L5-SO-ASC-04": {"modelo": "GEN2 COMFORT", "marca": "OTIS", "anos_op": 16, "fallas": 19, "criticos": 0}, "L5-SO-ASC-01": {"modelo": "GEN2 COMFORT", "marca": "OTIS", "anos_op": 16, "fallas": 24, "criticos": 0}, "L5-SO-ASC-02": {"modelo": "GEN2 COMFORT", "marca": "OTIS", "anos_op": 16, "fallas": 41, "criticos": 0}, "L5-SO-ASC-03": {"modelo": "GEN2 COMFORT", "marca": "OTIS", "anos_op": 16, "fallas": 14, "criticos": 0}, "L5-PR-ASC-01": {"modelo": "GEN2 COMFORT", "marca": "OTIS", "anos_op": 16, "fallas": 6, "criticos": 0}, "L5-PR-ASC-02": {"modelo": "GEN2 COMFORT", "marca": "OTIS", "anos_op": 16, "fallas": 7, "criticos": 0}, "L5-PR-ASC-03": {"modelo": "GEN2 COMFORT", "marca": "OTIS", "anos_op": 16, "fallas": 9, "criticos": 0}, "L5-PR-ASC-04": {"modelo": "GEN2 COMFORT", "marca": "OTIS", "anos_op": 16, "fallas": 8, "criticos": 0}, "L5-BL-ASC-01": {"modelo": "GEN2 COMFORT", "marca": "OTIS", "anos_op": 16, "fallas": 1, "criticos": 0}, "L5-BL-ASC-03": {"modelo": "GEN2 COMFORT", "marca": "OTIS", "anos_op": 16, "fallas": 55, "criticos": 1}, "L5-BL-ASC-02": {"modelo": "GEN2 COMFORT", "marca": "OTIS", "anos_op": 16, "fallas": 7, "criticos": 0}, "L5-GL-ASC-01": {"modelo": "GEN2 COMFORT", "marca": "OTIS", "anos_op": 16, "fallas": 15, "criticos": 0}, "L5-GL-ASC-02": {"modelo": "GEN2 COMFORT", "marca": "OTIS", "anos_op": 16, "fallas": 3, "criticos": 0}, "L5-GL-ASC-03": {"modelo": "GEN2 COMFORT", "marca": "OTIS", "anos_op": 16, "fallas": 101, "criticos": 0}, "L5-BQ-ASC-01": {"modelo": "GEN2 COMFORT", "marca": "OTIS", "anos_op": 15, "fallas": 19, "criticos": 0}, "L5-BQ-ASC-02": {"modelo": "ADV210", "marca": "OTIS", "anos_op": 29, "fallas": 64, "criticos": 0}, "L4A-SJU-ASC-03": {"modelo": "GEN2 LVA", "marca": "OTIS", "anos_op": 15, "fallas": 52, "criticos": 0}, "L4A-SJU-ASC-04": {"modelo": "GEN2 COMFORT", "marca": "OTIS", "anos_op": 15, "fallas": 26, "criticos": 0}, "L4A-LGR-ASC-03": {"modelo": "GEN2 COMFORT", "marca": "OTIS", "anos_op": 15, "fallas": 51, "criticos": 0}, "L4A-LGR-ASC-04": {"modelo": "GEN2 COMFORT", "marca": "OTIS", "anos_op": 15, "fallas": 27, "criticos": 0}, "L4A-SRA-ASC-03": {"modelo": "GEN2 COMFORT", "marca": "OTIS", "anos_op": 15, "fallas": 61, "criticos": 0}, "L4A-SRA-ASC-04": {"modelo": "GEN2 COMFORT", "marca": "OTIS", "anos_op": 15, "fallas": 40, "criticos": 0}, "L4A-LCI-ASC-01": {"modelo": "GEN2 COMFORT", "marca": "OTIS", "anos_op": 15, "fallas": 14, "criticos": 0}, "L5-IR-ASC-01": {"modelo": "ADV210", "marca": "OTIS", "anos_op": 29, "fallas": 23, "criticos": 0}, "L5-IR-ASC-02": {"modelo": "ADV210", "marca": "OTIS", "anos_op": 29, "fallas": 35, "criticos": 0}, "L5-LF-ASC-01": {"modelo": "ADV210", "marca": "OTIS", "anos_op": 29, "fallas": 60, "criticos": 0}, "L5-LF-ASC-02": {"modelo": "ADV210", "marca": "OTIS", "anos_op": 29, "fallas": 31, "criticos": 0}, "L2-HE-ASC-01": {"modelo": "GEN2 REGEN", "marca": "OTIS", "anos_op": 14, "fallas": 28, "criticos": 0}, "L2-HE-ASC-02": {"modelo": "GEN2 REGEN", "marca": "OTIS", "anos_op": 14, "fallas": 26, "criticos": 0}, "L2-HE-ASC-03": {"modelo": "GEN2 REGEN", "marca": "OTIS", "anos_op": 14, "fallas": 16, "criticos": 0}, "L2-HE-ASC-04": {"modelo": "GEN2 REGEN", "marca": "OTIS", "anos_op": 14, "fallas": 12, "criticos": 0}, "L1-LH-ASC-01": {"modelo": "GEN2 REGEN", "marca": "OTIS", "anos_op": 14, "fallas": 5, "criticos": 0}, "L1-LH-ASC-02": {"modelo": "GEN2 REGEN", "marca": "OTIS", "anos_op": 14, "fallas": 13, "criticos": 0}, "L1-LH-ASC-03": {"modelo": "GEN2 REGEN", "marca": "OTIS", "anos_op": 14, "fallas": 19, "criticos": 0}, "L1-LR-ASC-01": {"modelo": "GEN2 REGEN", "marca": "OTIS", "anos_op": 12, "fallas": 8, "criticos": 0}, "L1-LR-ASC-02": {"modelo": "GEN2 REGEN", "marca": "OTIS", "anos_op": 12, "fallas": 3, "criticos": 0}, "L1-EM-ASC-02": {"modelo": "GEN2 COMFORT", "marca": "OTIS", "anos_op": 16, "fallas": 13, "criticos": 0}, "L1-US-ASC-01": {"modelo": "GEN2 LVA", "marca": "OTIS", "anos_op": 7, "fallas": 40, "criticos": 0}, "L1-US-ASC-02": {"modelo": "GEN2 LVA", "marca": "OTIS", "anos_op": 7, "fallas": 31, "criticos": 0}, "L2-PQ-ASC-03": {"modelo": "GEN2 LVA", "marca": "OTIS", "anos_op": 7, "fallas": 38, "criticos": 0}, "L1-CCA-ASC-01": {"modelo": "KONE", "marca": "KONE", "anos_op": 29, "fallas": 8, "criticos": 0}, "L1-CCA-ASC-02": {"modelo": "SUR", "marca": "SUR", "anos_op": 37, "fallas": 12, "criticos": 0}, "L2-CVN-ASC-01": {"modelo": "ARCA III", "marca": "ORONA", "anos_op": 5, "fallas": 17, "criticos": 0}}